CHANGELOG
COPYRIGHT
INSTALL
LICENSE
MANIFEST.in
README.md
bank.xml
setup.py
tryton.cfg
./__init__.py
./bank.py
./bank.xml
./party.py
./tryton.cfg
./data/bank_ar.xml
./locale/es_AR.po
./view/bank_account_form.xml
./view/bank_form.xml
./view/bank_list.xml
data/bank_ar.xml
locale/es_AR.po
trytonar_bank_ar.egg-info/PKG-INFO
trytonar_bank_ar.egg-info/SOURCES.txt
trytonar_bank_ar.egg-info/dependency_links.txt
trytonar_bank_ar.egg-info/entry_points.txt
trytonar_bank_ar.egg-info/not-zip-safe
trytonar_bank_ar.egg-info/pbr.json
trytonar_bank_ar.egg-info/requires.txt
trytonar_bank_ar.egg-info/top_level.txt
view/bank_account_form.xml
view/bank_form.xml
view/bank_list.xml