Metadata-Version: 1.1
Name: trytonar-bank-ar
Version: 3.4.1
Summary: Module for banks of Argentina
Home-page: http://www.silix.com.ar
Author: Mario Puntin
Author-email: contacto@silix.com.ar
License: GPL-3
Platform: UNKNOWN
Classifier: Development Status :: 4 - Beta
Classifier: Environment :: Plugins
Classifier: Intended Audience :: Developers
Classifier: Intended Audience :: Financial and Insurance Industry
Classifier: Intended Audience :: Legal Industry
Classifier: License :: OSI Approved :: GNU General Public License (GPL)
Classifier: Natural Language :: English
Classifier: Natural Language :: Spanish
Classifier: Operating System :: OS Independent
Classifier: Programming Language :: Python :: 2.5
Classifier: Programming Language :: Python :: 2.6
Classifier: Programming Language :: Python :: 2.7
Classifier: Topic :: Office/Business
Classifier: Topic :: Office/Business :: Financial :: Accounting
